interkamen_career/__init__.py
interkamen_career/__version__.py
interkamen_career/main_script.py
interkamen_career/exl_blancs/drill_passport.xlsx
interkamen_career/exl_blancs/ktu.xlsx
interkamen_career/exl_blancs/real_salary.xlsx
interkamen_career/exl_blancs/scheme.png
interkamen_career/exl_blancs/scheme_ng.png
interkamen_career/exl_blancs/workers_salary.xlsx
interkamen_career/exl_blancs/Бланк табеля.xlsx
interkamen_career/html_blancs/career_status.html
interkamen_career/html_blancs/map.pdf
interkamen_career/modules/__init__.py
interkamen_career/modules/career_status.py
interkamen_career/modules/count_workers_salary.py
interkamen_career/modules/drill_instrument_report.py
interkamen_career/modules/drill_passports.py
interkamen_career/modules/main_career_report.py
interkamen_career/modules/mechanic_report.py
interkamen_career/modules/mechanics_economic.py
interkamen_career/modules/rating.py
interkamen_career/modules/report_analysis.py
interkamen_career/modules/work_calendar.py
interkamen_career/modules/workers_module.py
interkamen_career/modules/workers_salary.py
interkamen_career/modules/administration/__init__.py
interkamen_career/modules/administration/accesse_options.py
interkamen_career/modules/administration/logger_cfg.py
interkamen_career/modules/administration/users.py
interkamen_career/modules/support_modules/__init__.py
interkamen_career/modules/support_modules/custom_exceptions.py
interkamen_career/modules/support_modules/dump_to_exl.py
interkamen_career/modules/support_modules/emailed.py
interkamen_career/modules/support_modules/hi.py
interkamen_career/modules/support_modules/news.py
interkamen_career/modules/support_modules/reminder.py
interkamen_career/modules/support_modules/standart_functions.py
interkamen_career/news/01 HelloWorld.txt
interkamen_career/support_img/inter_header.png
interkamen_career-1.18.9.data/scripts/interkamen
interkamen_career-1.18.9.dist-info/LICENSE
interkamen_career-1.18.9.dist-info/METADATA
interkamen_career-1.18.9.dist-info/WHEEL
interkamen_career-1.18.9.dist-info/top_level.txt
interkamen_career-1.18.9.dist-info/RECORD
