Metadata-Version: 2.1
Name: interkamen-career
Version: 1.18.9
Summary: Manage mining company.
Home-page: https://github.com/Acetonen/Interkamen_career
Author: Anton Kovalev
Author-email: acetonen@gmail.com
License: MIT
Platform: UNKNOWN
Classifier: Environment :: Console
Classifier: Natural Language :: Russian
Classifier: License :: OSI Approved :: MIT License
Classifier: Programming Language :: Python :: 3.7
Classifier: Programming Language :: Python :: Implementation :: CPython
Requires-Python: >=3.7.0
Requires-Dist: pandas
Requires-Dist: matplotlib
Requires-Dist: openpyxl
Requires-Dist: pillow
Requires-Dist: sentry-sdk
Requires-Dist: bcrypt
Requires-Dist: dill
Requires-Dist: pycrypto
